taxidpro/__init__.py
taxidpro/main.py
taxidpro-1.0.2.dist-info/METADATA
taxidpro-1.0.2.dist-info/WHEEL
taxidpro-1.0.2.dist-info/licenses/LICENSE
taxidpro-1.0.2.dist-info/RECORD
