Metadata-Version: 2.3
Name: taxidpro
Version: 1.0.2
Summary: Tax ID Validation Library for Python
Project-URL: Homepage, https://github.com/balancer-team/taxidpro-py
Project-URL: Issues, https://github.com/balancer-team/taxidpro-py/issues
Author-email: Alan Hettinger <alan@balancer.team>
License-File: LICENSE
Classifier: License :: OSI Approved :: MIT License
Classifier: Operating System :: OS Independent
Classifier: Programming Language :: Python :: 3
Requires-Python: >=3.8
Requires-Dist: requests
Provides-Extra: dev
Requires-Dist: hatchling; extra == 'dev'
Requires-Dist: pytest; extra == 'dev'
Requires-Dist: twine; extra == 'dev'
